{"version":1,"newVersion":true,"labelName":"Date-30x30-01","paperType":2,"dpi":200,"labelWidth":31.0,"labelHeight":31.0,"printDirection":0,"backgroundImageUrl":"https://oss.qu-in.com/quinSystem/material/template/public/background/380150409614200833_Date-30x30-01bg.png","backgroundImageId":"380150409689698304","previewImageUrl":"https://oss.qu-in.com/quinSystem/material/template/public/screenshot/380150409698086912_Date-30x30-01s.png","previewImageId":"380150409765195776","adaptDevices":["M110","M200","M120"],"saveTimestamp":0,"thermalPrinter":true,"labelDirection":true,"pageMargins":[0,0],"controlInfos":[{"type":"shape","location":{"x":49,"y":165,"width":150,"height":39,"rotateAngle":0},"shapeInfo":{"shapeType":1,"lineWidth":2.0,"fill":false}},{"type":"timeStamp","location":{"x":53,"y":175,"width":142,"height":20,"rotateAngle":0},"textInfo":{"text":"24-June-22","fontID":"","fontName":"黑体","fontIntSize":20.0,"aligment":2,"bold":true,"italic":false,"underline":false,"strikethrough":false,"leading":0.0,"kerning":0.0,"lineSpace":1.0,"autoAddNumber":0,"autoAddCount":0,"blackBackground":false,"bFixedText":false},"timeStampInfo":{"timestamp":1656066189,"dateFormat":"dd/MM/yyyy","dateOffset":0,"autoUpdateTime":false,"timestampSelectIndex":"16"}},{"type":"text","location":{"x":34,"y":30,"width":181,"height":42,"rotateAngle":0},"textInfo":{"text":"Cranberry Cookies","fontID":"","fontName":"思源黑体","fontSize":"21","fontIntSize":21.0,"aligment":2,"bold":true,"italic":false,"underline":true,"strikethrough":false,"leading":0.0,"kerning":0.0,"lineSpace":1.0,"autoAddNumber":0,"autoAddCount":0,"blackBackground":false,"bFixedText":false}},{"type":"text","location":{"x":17,"y":94,"width":214,"height":45,"rotateAngle":0},"textInfo":{"text":"Ingredient:Low-gluten flour, powdered sugar, butter, dried cranberries, eggs, etc.","fontID":"","fontName":"思源黑体","fontSize":"15","fontIntSize":15.0,"aligment":2,"bold":false,"italic":false,"underline":false,"strikethrough":false,"leading":0.0,"kerning":0.0,"lineSpace":1.0,"autoAddNumber":0,"autoAddCount":0,"blackBackground":false,"bFixedText":false}}]}